dbt_py/__init__.py
dbt_py/config.py
dbt_py/exceptions.py
dbt_py/main.py
dbt_py_wrap-0.1.0.dist-info/licenses/LICENSE
dbt_py_wrap-0.1.0.dist-info/METADATA
dbt_py_wrap-0.1.0.dist-info/WHEEL
dbt_py_wrap-0.1.0.dist-info/entry_points.txt
dbt_py_wrap-0.1.0.dist-info/top_level.txt
dbt_py_wrap-0.1.0.dist-info/RECORD
