Metadata-Version: 2.4
Name: dbt-py-wrap
Version: 0.1.0
Summary: Python wrapper for dbt-core to extend dbt with custom Python.
Author: billwallis
License: MIT License
Requires-Python: >=3.11
License-File: LICENSE
Requires-Dist: dbt-core>=1.5.0
Dynamic: license-file
